excel_to_dto/__init__.py
excel_to_dto/exceptions.py
excel_to_dto/models.py
excel_to_dto/parsers.py
excel_to_dto/py.typed
excel_to_dto/utils.py
excel_to_dto-0.1.0.dist-info/METADATA
excel_to_dto-0.1.0.dist-info/WHEEL
excel_to_dto-0.1.0.dist-info/licenses/LICENSE
excel_to_dto-0.1.0.dist-info/RECORD
