Metadata-Version: 2.4
Name: excel-to-dto
Version: 0.1.0
Summary: Библиотека для парсинга и валидации данных из Excel файлов с автоматическим преобразованием в dataclass модели
License-File: LICENSE
Author: DmitryM
Author-email: inood@ya.ru
Requires-Python: >=3.10,<4.0
Classifier: Programming Language :: Python :: 3
Classifier: Programming Language :: Python :: 3.10
Classifier: Programming Language :: Python :: 3.11
Classifier: Programming Language :: Python :: 3.12
Classifier: Programming Language :: Python :: 3.13
Classifier: Programming Language :: Python :: 3.14
Requires-Dist: openpyxl (>=3.1.2,<4.0.0)
Requires-Dist: pydantic (>=2.5.0,<3.0.0)
Requires-Dist: typing-extensions (>=4.8.0,<5.0.0)
